qpandas/__init__.py
qpandas/qpandas.py
qpandas/data/births.csv
qpandas/data/births_by_month.csv
qpandas/data/meat.csv
qpandas-1.0.2.dist-info/METADATA
qpandas-1.0.2.dist-info/WHEEL
qpandas-1.0.2.dist-info/licenses/LICENSE
qpandas-1.0.2.dist-info/RECORD
