Metadata-Version: 2.1
Name: qpandas
Version: 1.0.2
Summary: Query Panadas DataFrames with SQL
Project-URL: Homepage, https://github.com/yrom1/qpandas
Project-URL: Bug Tracker, https://github.com/yrom1/qpandas/issues
Author-email: yrom1 <ryanm.inbox@gmail.com>
License-Expression: MIT
License-File: LICENSE
Classifier: License :: OSI Approved :: MIT License
Classifier: Operating System :: OS Independent
Classifier: Programming Language :: Python :: 3
Requires-Python: >=3.10
Requires-Dist: pandas
Requires-Dist: sqlalchemy
Requires-Dist: sqlglot
